lda/LDABYRB.py
lda/__init__.py
LDABYRB-0.1.1.dist-info/LICENSE.txt
LDABYRB-0.1.1.dist-info/METADATA
LDABYRB-0.1.1.dist-info/WHEEL
LDABYRB-0.1.1.dist-info/top_level.txt
LDABYRB-0.1.1.dist-info/RECORD
