Metadata-Version: 2.1
Name: LDABYRB
Version: 0.1.1
Summary: long description
Home-page: https://github.com/BillyWangwzx/LDA-with-python
Author: Zhen Han Si & Zixi Wang
Author-email: zs85@duke.edu
License: UNKNOWN
Platform: UNKNOWN
Classifier: Programming Language :: Python :: 3
Classifier: License :: OSI Approved :: MIT License
Classifier: Operating System :: OS Independent
Requires-Dist: pandas (>=0.20.0)
